[{"name":"snail","qualifiedName":"snail","href":"snail/","kind":9,"packageRank":0,"desc":""},{"name":"Snail","qualifiedName":"snail.Snail","href":"snail/Snail-class.html","kind":3,"packageRank":0,"desc":"A database handler for SQLite that simplifies the database initialization\nand table creation process in Flutter/Dart applications.","enclosedBy":{"name":"snail","kind":9,"href":"snail/"}},{"name":"Snail","qualifiedName":"snail.Snail.Snail","href":"snail/Snail/Snail.html","kind":2,"packageRank":0,"desc":"","enclosedBy":{"name":"Snail","kind":3,"href":"snail/Snail-class.html"}},{"name":"getDatabase","qualifiedName":"snail.Snail.getDatabase","href":"snail/Snail/getDatabase.html","kind":10,"overriddenDepth":0,"packageRank":0,"desc":"Returns the instance of the database.","enclosedBy":{"name":"Snail","kind":3,"href":"snail/Snail-class.html"}},{"name":"initialize","qualifiedName":"snail.Snail.initialize","href":"snail/Snail/initialize.html","kind":10,"overriddenDepth":0,"packageRank":0,"desc":"Initializes the SQLite database and creates tables for the provided repositories.","enclosedBy":{"name":"Snail","kind":3,"href":"snail/Snail-class.html"}},{"name":"SnailRepository","qualifiedName":"snail.SnailRepository","href":"snail/SnailRepository-class.html","kind":3,"packageRank":0,"desc":"A base class for repositories that handle the operations on database tables.","enclosedBy":{"name":"snail","kind":9,"href":"snail/"}},{"name":"SnailRepository","qualifiedName":"snail.SnailRepository.SnailRepository","href":"snail/SnailRepository/SnailRepository.html","kind":2,"packageRank":0,"desc":"Creates an instance of SnailRepository with the specified table name,\nprimary key column, and field definitions.","enclosedBy":{"name":"SnailRepository","kind":3,"href":"snail/SnailRepository-class.html"}},{"name":"create","qualifiedName":"snail.SnailRepository.create","href":"snail/SnailRepository/create.html","kind":10,"overriddenDepth":0,"packageRank":0,"desc":"Inserts a new item into the database.","enclosedBy":{"name":"SnailRepository","kind":3,"href":"snail/SnailRepository-class.html"}},{"name":"createMany","qualifiedName":"snail.SnailRepository.createMany","href":"snail/SnailRepository/createMany.html","kind":10,"overriddenDepth":0,"packageRank":0,"desc":"Inserts multiple items into the database.","enclosedBy":{"name":"SnailRepository","kind":3,"href":"snail/SnailRepository-class.html"}},{"name":"defineFields","qualifiedName":"snail.SnailRepository.defineFields","href":"snail/SnailRepository/defineFields.html","kind":16,"overriddenDepth":0,"packageRank":0,"desc":"","enclosedBy":{"name":"SnailRepository","kind":3,"href":"snail/SnailRepository-class.html"}},{"name":"delete","qualifiedName":"snail.SnailRepository.delete","href":"snail/SnailRepository/delete.html","kind":10,"overriddenDepth":0,"packageRank":0,"desc":"Deletes an item by its ID from the database.","enclosedBy":{"name":"SnailRepository","kind":3,"href":"snail/SnailRepository-class.html"}},{"name":"deleteMany","qualifiedName":"snail.SnailRepository.deleteMany","href":"snail/SnailRepository/deleteMany.html","kind":10,"overriddenDepth":0,"packageRank":0,"desc":"Deletes multiple items by their IDs from the database.","enclosedBy":{"name":"SnailRepository","kind":3,"href":"snail/SnailRepository-class.html"}},{"name":"findMany","qualifiedName":"snail.SnailRepository.findMany","href":"snail/SnailRepository/findMany.html","kind":10,"overriddenDepth":0,"packageRank":0,"desc":"Retrieves all items from the database.","enclosedBy":{"name":"SnailRepository","kind":3,"href":"snail/SnailRepository-class.html"}},{"name":"findOne","qualifiedName":"snail.SnailRepository.findOne","href":"snail/SnailRepository/findOne.html","kind":10,"overriddenDepth":0,"packageRank":0,"desc":"Retrieves a single item by its ID from the database.","enclosedBy":{"name":"SnailRepository","kind":3,"href":"snail/SnailRepository-class.html"}},{"name":"fromMap","qualifiedName":"snail.SnailRepository.fromMap","href":"snail/SnailRepository/fromMap.html","kind":10,"overriddenDepth":0,"packageRank":0,"desc":"Converts a map from the database to an entity of type T.","enclosedBy":{"name":"SnailRepository","kind":3,"href":"snail/SnailRepository-class.html"}},{"name":"generateCreateTableQuery","qualifiedName":"snail.SnailRepository.generateCreateTableQuery","href":"snail/SnailRepository/generateCreateTableQuery.html","kind":10,"overriddenDepth":0,"packageRank":0,"desc":"Generates the SQL query to create the table for this repository.","enclosedBy":{"name":"SnailRepository","kind":3,"href":"snail/SnailRepository-class.html"}},{"name":"primaryKeyColumn","qualifiedName":"snail.SnailRepository.primaryKeyColumn","href":"snail/SnailRepository/primaryKeyColumn.html","kind":16,"overriddenDepth":0,"packageRank":0,"desc":"","enclosedBy":{"name":"SnailRepository","kind":3,"href":"snail/SnailRepository-class.html"}},{"name":"tableName","qualifiedName":"snail.SnailRepository.tableName","href":"snail/SnailRepository/tableName.html","kind":16,"overriddenDepth":0,"packageRank":0,"desc":"","enclosedBy":{"name":"SnailRepository","kind":3,"href":"snail/SnailRepository-class.html"}},{"name":"toMap","qualifiedName":"snail.SnailRepository.toMap","href":"snail/SnailRepository/toMap.html","kind":10,"overriddenDepth":0,"packageRank":0,"desc":"Converts an entity of type T to a map that can be inserted into the database.","enclosedBy":{"name":"SnailRepository","kind":3,"href":"snail/SnailRepository-class.html"}},{"name":"update","qualifiedName":"snail.SnailRepository.update","href":"snail/SnailRepository/update.html","kind":10,"overriddenDepth":0,"packageRank":0,"desc":"Updates an existing item in the database.","enclosedBy":{"name":"SnailRepository","kind":3,"href":"snail/SnailRepository-class.html"}},{"name":"updateMany","qualifiedName":"snail.SnailRepository.updateMany","href":"snail/SnailRepository/updateMany.html","kind":10,"overriddenDepth":0,"packageRank":0,"desc":"Updates multiple items in the database.","enclosedBy":{"name":"SnailRepository","kind":3,"href":"snail/SnailRepository-class.html"}}]
